phased_lstm_keras/PhasedLSTM.py
phased_lstm_keras/__init__.py
phased_lstm_keras-1.0.2.dist-info/DESCRIPTION.rst
phased_lstm_keras-1.0.2.dist-info/METADATA
phased_lstm_keras-1.0.2.dist-info/RECORD
phased_lstm_keras-1.0.2.dist-info/WHEEL
phased_lstm_keras-1.0.2.dist-info/metadata.json
phased_lstm_keras-1.0.2.dist-info/top_level.txt
