Metadata-Version: 2.0
Name: phased-lstm-keras
Version: 1.0.2
Summary: Keras implementation of Phased LSTM
Home-page: https://github.com/fferroni/PhasedLSTM-Keras
Author: Francesco Ferroni
Author-email: francescoferroni1@gmail.com
License: GPLv3+
Keywords: machinelearning deeplearning development
Platform: UNKNOWN
Classifier: Development Status :: 4 - Beta
Classifier: Intended Audience :: Developers
Classifier: Topic :: Scientific/Engineering :: Artificial Intelligence
Classifier: License :: OSI Approved :: GNU General Public License v3 or later (GPLv3+)
Classifier: Programming Language :: Python :: 2
Classifier: Programming Language :: Python :: 2.7
Classifier: Programming Language :: Python :: 3
Classifier: Programming Language :: Python :: 3.3
Classifier: Programming Language :: Python :: 3.4
Classifier: Programming Language :: Python :: 3.5
Requires-Dist: keras (>=2.0.2)
Requires-Dist: matplotlib (>=2.0.0)
Requires-Dist: numpy (>=1.12.1)
